uedition/__about__.py
uedition/__init__.py
uedition/__main__.py
uedition/settings.py
uedition/cli/__init__.py
uedition/cli/base.py
uedition/cli/build.py
uedition/cli/init.py
uedition/cli/language.py
uedition/cli/migrate.py
uedition/cli/serve.py
uedition/cli/update.py
uedition/ext/__init__.py
uedition/ext/config.py
uedition/ext/language_switcher.css
uedition/ext/language_switcher.js
uedition/ext/language_switcher.py
uedition/ext/settings.py
uedition/ext/tei/__init__.py
uedition/ext/tei/builder.py
uedition/ext/tei/parser.py
uedition/ext/tei/tei_download.js
uedition-2.0.0.dist-info/METADATA
uedition-2.0.0.dist-info/WHEEL
uedition-2.0.0.dist-info/entry_points.txt
uedition-2.0.0.dist-info/licenses/LICENSE.txt
uedition-2.0.0.dist-info/RECORD
