Metadata-Version: 2.4
Name: uEdition
Version: 2.0.0
Project-URL: Documentation, https://github.com/uEdition/uEdition#readme
Project-URL: Issues, https://github.com/uEdition/uEdition/issues
Project-URL: Source, https://github.com/uEdition/uEdition
Author-email: Mark Hall <mark.hall@work.room3b.eu>
License-Expression: MIT
License-File: LICENSE.txt
Classifier: Development Status :: 4 - Beta
Classifier: Programming Language :: Python
Classifier: Programming Language :: Python :: 3.10
Classifier: Programming Language :: Python :: 3.11
Classifier: Programming Language :: Python :: 3.12
Classifier: Programming Language :: Python :: 3.13
Classifier: Programming Language :: Python :: Implementation :: CPython
Classifier: Programming Language :: Python :: Implementation :: PyPy
Requires-Python: >=3.10
Requires-Dist: httpx<0.29,>=0.28.1
Requires-Dist: livereload
Requires-Dist: lxml<6.0.0,>=4.9.2
Requires-Dist: myst-parser<5,>=4.0.1
Requires-Dist: packaging==24.2
Requires-Dist: pydantic-settings<3.0.0,>=2.0.0
Requires-Dist: pydantic<3.0.0,>=2.0.0
Requires-Dist: pyyaml<7.0.0,>=6.0.0
Requires-Dist: sphinx-book-theme<2,>=1.1.4
Requires-Dist: sphinx-external-toc<2,>=1.0.1
Requires-Dist: sphinx<9,>=8.2.3
Requires-Dist: strictyaml<2,>=1.7.3
Requires-Dist: tomlkit<0.14,>=0.13.2
Requires-Dist: typer<1.0.0
